{
	"configurations" : 
	[
		{
			"directories" : 
			[
				{
					"build" : ".",
					"jsonFile" : "directory-.-Debug-f5ebdc15457944623624.json",
					"minimumCMakeVersion" : 
					{
						"string" : "3.22"
					},
					"projectIndex" : 0,
					"source" : ".",
					"targetIndexes" : 
					[
						0
					]
				}
			],
			"name" : "Debug",
			"projects" : 
			[
				{
					"directoryIndexes" : 
					[
						0
					],
					"name" : "MipsAssembler",
					"targetIndexes" : 
					[
						0
					]
				}
			],
			"targets" : 
			[
				{
					"directoryIndex" : 0,
					"id" : "MipsAssembler::@6890427a1f51a3e7e1df",
					"jsonFile" : "target-MipsAssembler-Debug-7632df765aaee9dcb057.json",
					"name" : "MipsAssembler",
					"projectIndex" : 0
				}
			]
		}
	],
	"kind" : "codemodel",
	"paths" : 
	{
		"build" : "/Users/sajeeb/Downloads/MIPS32CPUwithAssembler/MipsAssembler/cmake-build-debug",
		"source" : "/Users/sajeeb/Downloads/MIPS32CPUwithAssembler/MipsAssembler"
	},
	"version" : 
	{
		"major" : 2,
		"minor" : 6
	}
}
